coderedo/__init__.py
coderedo/__main__.py
coderedo/utils/Class.py
coderedo/utils/__init__.py
coderedo/utils/functions.py
coderedo-2.1.0.dist-info/LICENSE
coderedo-2.1.0.dist-info/METADATA
coderedo-2.1.0.dist-info/WHEEL
coderedo-2.1.0.dist-info/top_level.txt
coderedo-2.1.0.dist-info/RECORD
