Metadata-Version: 2.1
Name: coderedo
Version: 2.1.0
Home-page: https://github.com/Ridoineel/coderedo
Author: RidoineEl
Author-email: ridoineelofficiel@gmail.com
Project-URL: Bug Tracker, https://github.com/Ridoineel/coderedo/log-module/issues
Classifier: Programming Language :: Python :: 3
Classifier: License :: OSI Approved :: MIT License
Classifier: Operating System :: OS Independent
Requires-Python: >=3.6
License-File: LICENSE
